style_table/__init__.py
style_table/style_table.py
style_table-0.1.1.dist-info/LICENSE
style_table-0.1.1.dist-info/METADATA
style_table-0.1.1.dist-info/WHEEL
style_table-0.1.1.dist-info/top_level.txt
style_table-0.1.1.dist-info/RECORD
