Metadata-Version: 2.1
Name: style_table
Version: 0.1.1
Summary: A library for styling pandas DataFrames in Jupyter Notebooks
Home-page: https://github.com/yourusername/style_table.py
Author: Jose Luis Garcia Tucci
Author-email: jlgarciatucci@gmail.com
License: MIT
Classifier: Programming Language :: Python :: 3
Classifier: License :: OSI Approved :: MIT License
Classifier: Operating System :: OS Independent
License-File: LICENSE
Requires-Dist: pandas
